.gitignore
.gitlab-ci.yml
README.md
environment.yml
pyproject.toml
requirements.txt
setup.cfg
setup.py
tox.ini
docs/Makefile
docs/conf.py
docs/index.rst
docs/make.bat
scln_client/__init__.py
scln_client/scln_client.py
scln_client.egg-info/PKG-INFO
scln_client.egg-info/SOURCES.txt
scln_client.egg-info/dependency_links.txt
scln_client.egg-info/entry_points.txt
scln_client.egg-info/not-zip-safe
scln_client.egg-info/requires.txt
scln_client.egg-info/top_level.txt
scln_client/tests/__init__.py
scln_client/tests/test_scln_client.py