Metadata-Version: 2.1
Name: scln-client
Version: 1.0.1
Summary: Python Client for the SOAR Communication Library
Home-page: https://gitlab.com/nsf-noirlab/soar/py-scln-client
Author: Diego Gomez, Simon Torres
Author-email: diego.gomez@noirlab.edu, simon.torres@noirlab.edu
License: BSD-3-Clause
Platform: UNKNOWN
Requires-Python: >=3.7
Provides-Extra: test
